pruna/__init__.py
pruna/py.typed
pruna/smash.py
pruna/algorithms/__init__.py
pruna/algorithms/c_translate.py
pruna/algorithms/deepcache.py
pruna/algorithms/fastercache.py
pruna/algorithms/flash_attn3.py
pruna/algorithms/fora.py
pruna/algorithms/gptq_model.py
pruna/algorithms/half.py
pruna/algorithms/hqq.py
pruna/algorithms/hqq_diffusers.py
pruna/algorithms/huggingface_diffusers_int8.py
pruna/algorithms/huggingface_llm_int8.py
pruna/algorithms/ifw.py
pruna/algorithms/llm_compressor.py
pruna/algorithms/pab.py
pruna/algorithms/qkv_diffusers.py
pruna/algorithms/quanto.py
pruna/algorithms/stable_fast.py
pruna/algorithms/torch_dynamic.py
pruna/algorithms/torch_structured.py
pruna/algorithms/torch_unstructured.py
pruna/algorithms/torchao.py
pruna/algorithms/ws2t.py
pruna/algorithms/base/__init__.py
pruna/algorithms/base/pruna_base.py
pruna/algorithms/base/registry.py
pruna/algorithms/base/tags.py
pruna/algorithms/torch_compile/__init__.py
pruna/algorithms/torch_compile/generators.py
pruna/algorithms/torch_compile/torch_compile.py
pruna/config/__init__.py
pruna/config/hyperparameters.py
pruna/config/pre_smash_routines.py
pruna/config/smash_config.py
pruna/config/smash_space.py
pruna/config/target_modules.py
pruna/config/utils.py
pruna/data/__init__.py
pruna/data/collate.py
pruna/data/pruna_datamodule.py
pruna/data/utils.py
pruna/data/datasets/audio.py
pruna/data/datasets/image.py
pruna/data/datasets/prompt.py
pruna/data/datasets/question_answering.py
pruna/data/datasets/text_generation.py
pruna/data/datasets/text_to_image.py
pruna/data/datasets/text_to_video.py
pruna/engine/__init__.py
pruna/engine/call_sequence_tracker.py
pruna/engine/load.py
pruna/engine/model_checks.py
pruna/engine/pruna_model.py
pruna/engine/save.py
pruna/engine/utils.py
pruna/engine/handler/handler_autoregressive.py
pruna/engine/handler/handler_diffuser.py
pruna/engine/handler/handler_inference.py
pruna/engine/handler/handler_pipeline.py
pruna/engine/handler/handler_standard.py
pruna-0.3.0.dist-info/METADATA
pruna-0.3.0.dist-info/WHEEL
pruna-0.3.0.dist-info/licenses/LICENSE
pruna-0.3.0.dist-info/RECORD
