Metadata-Version: 2.4
Name: pruna
Version: 0.3.0
Summary: Smash your AI models
Author-email: Pruna AI <hello@pruna.ai>
License: Copyright 2025 - Pruna AI GmbH. All rights reserved.
License-File: LICENSE
Keywords: AI,machine learning,model optimization,pruning
Classifier: Development Status :: 4 - Beta
Classifier: Intended Audience :: Developers
Classifier: Programming Language :: Python :: 3
Classifier: Programming Language :: Python :: 3.9
Classifier: Programming Language :: Python :: 3.10
Classifier: Programming Language :: Python :: 3.11
Classifier: Programming Language :: Python :: 3.12
Requires-Python: <3.13,>=3.9
Requires-Dist: aenum
Requires-Dist: bitsandbytes; sys_platform != 'darwin' or platform_machine != 'arm64'
Requires-Dist: codecarbon
Requires-Dist: colorama
Requires-Dist: configspace>=1.2.1
Requires-Dist: ctranslate2==4.6.0
Requires-Dist: datasets>=0.34
Requires-Dist: deepcache
Requires-Dist: diffusers>=0.21.4
Requires-Dist: gliner; python_version >= '3.10'
Requires-Dist: hqq==0.2.7.post1
Requires-Dist: huggingface-hub[hf-xet]>=0.30.0
Requires-Dist: imageio-ffmpeg
Requires-Dist: jaxtyping
Requires-Dist: kernels
Requires-Dist: librosa
Requires-Dist: llmcompressor
Requires-Dist: numpy>=1.24.4
Requires-Dist: opencv-python
Requires-Dist: opentelemetry-api>=1.30.0
Requires-Dist: opentelemetry-exporter-otlp>=1.29.0
Requires-Dist: opentelemetry-sdk>=1.30.0
Requires-Dist: openvino
Requires-Dist: optimum-quanto>=0.2.5
Requires-Dist: piq
Requires-Dist: pynvml
Requires-Dist: pytorch-lightning
Requires-Dist: requests>=2.31.0
Requires-Dist: sentencepiece
Requires-Dist: soundfile
Requires-Dist: thop
Requires-Dist: timm
Requires-Dist: torch-pruning
Requires-Dist: torch==2.7.0
Requires-Dist: torchao
Requires-Dist: torchmetrics[image]==1.7.4
Requires-Dist: torchvision==0.22.0
Requires-Dist: transformers
Requires-Dist: vbench-pruna; sys_platform != 'darwin'
Requires-Dist: whisper-s2t==1.3.1
Provides-Extra: cpu
Provides-Extra: dev
Requires-Dist: blobfile; extra == 'dev'
Requires-Dist: coverage; extra == 'dev'
Requires-Dist: docutils; extra == 'dev'
Requires-Dist: ipykernel; extra == 'dev'
Requires-Dist: jsonschema; extra == 'dev'
Requires-Dist: jupyterlab; extra == 'dev'
Requires-Dist: logbar; extra == 'dev'
Requires-Dist: notebook; extra == 'dev'
Requires-Dist: numpydoc-validation; extra == 'dev'
Requires-Dist: pillow>=9.5.0; extra == 'dev'
Requires-Dist: platformdirs; extra == 'dev'
Requires-Dist: pre-commit; extra == 'dev'
Requires-Dist: pyc-wheel; extra == 'dev'
Requires-Dist: pytest; extra == 'dev'
Requires-Dist: pytest-cov; extra == 'dev'
Requires-Dist: pytest-rerunfailures; extra == 'dev'
Requires-Dist: pytest-xdist>=3.8.0; extra == 'dev'
Requires-Dist: python-dotenv; extra == 'dev'
Requires-Dist: ruff; extra == 'dev'
Requires-Dist: twine; extra == 'dev'
Requires-Dist: ty; extra == 'dev'
Requires-Dist: types-pyyaml; extra == 'dev'
Requires-Dist: wget; extra == 'dev'
Provides-Extra: full
Requires-Dist: stable-fast-pruna==1.0.7; extra == 'full'
Requires-Dist: xformers==0.0.30; extra == 'full'
Provides-Extra: gptq
Requires-Dist: device-smi; extra == 'gptq'
Requires-Dist: gptqmodel; (sys_platform == 'darwin' and platform_machine == 'arm64') and extra == 'gptq'
Requires-Dist: gptqmodel==4.0.0.dev0+cu126torch2.7; (sys_platform != 'darwin' or platform_machine != 'arm64') and extra == 'gptq'
Requires-Dist: logbar; extra == 'gptq'
Requires-Dist: random-word; extra == 'gptq'
Requires-Dist: threadpoolctl; extra == 'gptq'
Requires-Dist: tokenicer; extra == 'gptq'
Provides-Extra: stable-fast
Requires-Dist: stable-fast-pruna==1.0.7; extra == 'stable-fast'
Requires-Dist: xformers==0.0.30; extra == 'stable-fast'
